evoxbench/__init__.py
evoxbench/api/__init__.py
evoxbench/api/rpc.py
evoxbench/benchmarks/__init__.py
evoxbench/benchmarks/darts.py
evoxbench/benchmarks/mnv3.py
evoxbench/benchmarks/mosegnas.py
evoxbench/benchmarks/nats.py
evoxbench/benchmarks/nb101.py
evoxbench/benchmarks/nb201.py
evoxbench/benchmarks/resnet.py
evoxbench/benchmarks/transformer.py
evoxbench/database/__init__.py
evoxbench/database/init.py
evoxbench/database/manage.py
evoxbench/database/ORM/__init__.py
evoxbench/database/ORM/asgi.py
evoxbench/database/ORM/settings.py
evoxbench/database/ORM/urls.py
evoxbench/database/ORM/wsgi.py
evoxbench/database/darts/__init__.py
evoxbench/database/darts/admin.py
evoxbench/database/darts/apps.py
evoxbench/database/darts/models.py
evoxbench/database/darts/tests.py
evoxbench/database/darts/views.py
evoxbench/database/darts/migrations/0001_initial.py
evoxbench/database/darts/migrations/__init__.py
evoxbench/database/hw_nas_bench_api/__init__.py
evoxbench/database/hw_nas_bench_api/hw_nas_bench_api.py
evoxbench/database/hw_nas_bench_api/fbnet_models/__init__.py
evoxbench/database/hw_nas_bench_api/fbnet_models/model_infer.py
evoxbench/database/hw_nas_bench_api/nas_201_models/CifarDenseNet.py
evoxbench/database/hw_nas_bench_api/nas_201_models/CifarResNet.py
evoxbench/database/hw_nas_bench_api/nas_201_models/CifarWideResNet.py
evoxbench/database/hw_nas_bench_api/nas_201_models/ImageNet_MobileNetV2.py
evoxbench/database/hw_nas_bench_api/nas_201_models/ImageNet_ResNet.py
evoxbench/database/hw_nas_bench_api/nas_201_models/SharedUtils.py
evoxbench/database/hw_nas_bench_api/nas_201_models/__init__.py
evoxbench/database/hw_nas_bench_api/nas_201_models/cell_operations.py
evoxbench/database/hw_nas_bench_api/nas_201_models/clone_weights.py
evoxbench/database/hw_nas_bench_api/nas_201_models/initialization.py
evoxbench/database/hw_nas_bench_api/nas_201_models/cell_infers/__init__.py
evoxbench/database/hw_nas_bench_api/nas_201_models/cell_infers/cells.py
evoxbench-1.0.5.dist-info/LICENSE
evoxbench-1.0.5.dist-info/METADATA
evoxbench-1.0.5.dist-info/NOTICE
evoxbench-1.0.5.dist-info/WHEEL
evoxbench-1.0.5.dist-info/entry_points.txt
evoxbench-1.0.5.dist-info/top_level.txt
evoxbench-1.0.5.dist-info/RECORD
