Metadata-Version: 2.1
Name: evoxbench
Version: 1.0.5
Summary: A benchmark for NAS algorithms
Home-page: https://github.com/EMI-Group/evoxbench
Author: EMI-Group
Author-email: emi-group@outlook.com
Project-URL: Bug Reports, https://github.com/EMI-Group/evoxbench/issues
Project-URL: Source, https://github.com/EMI-Group/evoxbench
Keywords: benchmark,evolution algorithm,neural architecture search
Classifier: Development Status :: 3 - Alpha
Classifier: Intended Audience :: Science/Research
Classifier: Topic :: Software Development :: Build Tools
Classifier: License :: OSI Approved :: MIT License
Classifier: Programming Language :: Python :: 3
Classifier: Programming Language :: Python :: 3.7
Classifier: Programming Language :: Python :: 3.8
Classifier: Programming Language :: Python :: 3.9
Classifier: Programming Language :: Python :: 3.10
Classifier: Programming Language :: Python :: 3 :: Only
Requires-Python: >=3.7, <4
License-File: LICENSE
License-File: NOTICE
Requires-Dist: pyyaml
Requires-Dist: django
Requires-Dist: numpy
Requires-Dist: scikit-learn
Requires-Dist: scipy
